discord/ext/modal_paginator/__init__.py
discord/ext/modal_paginator/core.py
discord/ext/modal_paginator/custom_button.py
discord/ext/modal_paginator/default_buttons.py
discord/ext/modal_paginator/errors.py
discord/ext/modal_paginator/utils.py
discord_ext_modal_paginator-1.3.0.dist-info/licenses/LICENSE
discord_ext_modal_paginator-1.3.0.dist-info/METADATA
discord_ext_modal_paginator-1.3.0.dist-info/WHEEL
discord_ext_modal_paginator-1.3.0.dist-info/top_level.txt
discord_ext_modal_paginator-1.3.0.dist-info/RECORD
