Metadata-Version: 2.4
Name: discord-ext-modal-paginator
Version: 1.3.0
Summary: An extension for discord.py that allows you to paginate a Modal using buttons.
Author: Soheab_
License-Expression: MPL-2.0
Project-URL: homepage, https://github.com/Soheab/modal-paginator
Project-URL: documentation, https://discord-ext-modal-paginator.readthedocs.io/
Project-URL: repository, https://github.com/Soheab/modal-paginator
Keywords: discord.py,dpy,discord,extension,discord.ext,modal,forum
Classifier: Development Status :: 5 - Production/Stable
Classifier: Natural Language :: English
Classifier: Typing :: Typed
Classifier: Programming Language :: Python :: 3 :: Only
Classifier: Programming Language :: Python :: 3.8
Classifier: Programming Language :: Python :: 3.9
Classifier: Programming Language :: Python :: 3.10
Classifier: Programming Language :: Python :: 3.11
Requires-Python: >=3.8
License-File: LICENSE
Requires-Dist: discord.py<3.0.0,>=2.2.0
Provides-Extra: dev
Requires-Dist: black; extra == "dev"
Requires-Dist: ruff; extra == "dev"
Requires-Dist: typing_extensions; extra == "dev"
Provides-Extra: docs
Requires-Dist: Sphinx<9,>=8.2; extra == "docs"
Requires-Dist: furo<2025,>=2024.8; extra == "docs"
Requires-Dist: sphinx-autodoc-typehints<4,>=3.2; extra == "docs"
Requires-Dist: enum-tools[sphinx]<0.14,>=0.13; extra == "docs"
Dynamic: license-file
